doru/__init__.py
doru/api/__init__.py
doru/api/app.py
doru/api/client.py
doru/api/daemonize.py
doru/api/router.py
doru/api/schema.py
doru/api/session.py
doru/cli.py
doru/envs.py
doru/exceptions.py
doru/exchange.py
doru/logger.py
doru/main.py
doru/manager/container.py
doru/manager/credential_manager.py
doru/manager/task_manager.py
doru/manager/utils.py
doru/scheduler.py
doru/type.py
doru-0.1.0.dist-info/LICENSE
doru-0.1.0.dist-info/METADATA
doru-0.1.0.dist-info/WHEEL
doru-0.1.0.dist-info/entry_points.txt
doru-0.1.0.dist-info/RECORD
