Metadata-Version: 2.1
Name: doru
Version: 0.1.0
Summary: A tiny command line tool for regular investment of cryptocurrencies on centralized exchanges using dollar-cost averaging.
Home-page: https://github.com/masa-08/doru
License: MIT
Author: Masaharu Shimizu
Author-email: masaharu.shimizu08@gmail.com
Requires-Python: >=3.7,<4.0
Classifier: License :: OSI Approved :: MIT License
Classifier: Programming Language :: Python :: 3
Classifier: Programming Language :: Python :: 3.7
Classifier: Programming Language :: Python :: 3.8
Classifier: Programming Language :: Python :: 3.9
Classifier: Programming Language :: Python :: 3.10
Classifier: Programming Language :: Python :: 3.11
Requires-Dist: backoff (>=2.2.1,<3.0.0)
Requires-Dist: ccxt (>=2.8.37,<3.0.0)
Requires-Dist: click (>=8.1.3,<9.0.0)
Requires-Dist: dependency-injector (>=4.41.0,<5.0.0)
Requires-Dist: fastapi (>=0.89.1,<0.90.0)
Requires-Dist: nanoid (>=2.0.0,<3.0.0)
Requires-Dist: pid (>=3.0.4,<4.0.0)
Requires-Dist: pydantic (>=1.10.2,<2.0.0)
Requires-Dist: python-daemon (>=2.3.2,<3.0.0)
Requires-Dist: requests-unixsocket (>=0.3.0,<0.4.0)
Requires-Dist: retry (>=0.9.2,<0.10.0)
Requires-Dist: schedule (>=1.1.0,<2.0.0)
Requires-Dist: tabulate (>=0.9.0,<0.10.0)
Requires-Dist: uvicorn (>=0.20.0,<0.21.0)
Project-URL: Repository, https://github.com/masa-08/doru
